{
  "domain": "tryhackme.com",
  "timestamp": "2025-06-13T22:12:23.460298",
  "total_subdomains_found": 23,
  "live_subdomains_count": 9,
  "subdomains": [
    [
      "lp.tryhackme.com",
      "Unknown"
    ],
    [
      "remote.tryhackme.com",
      "Unknown"
    ],
    [
      "auth.tryhackme.com",
      "Unknown"
    ],
    [
      "setup.auth.tryhackme.com",
      "Unknown"
    ],
    [
      "blog.tryhackme.com",
      "172.67.27.10"
    ],
    [
      "business.tryhackme.com",
      "Unknown"
    ],
    [
      "help.tryhackme.com",
      "172.67.27.10"
    ],
    [
      "www.tryhackme.com",
      "Unknown"
    ],
    [
      "remote-us-west-1.tryhackme.com",
      "Unknown"
    ],
    [
      "cancel.tryhackme.com",
      "Unknown"
    ],
    [
      "resources.tryhackme.com",
      "Unknown"
    ],
    [
      "newhelp.tryhackme.com",
      "Unknown"
    ],
    [
      "www.tryhackme.com",
      "104.22.55.228"
    ],
    [
      "admin.tryhackme.com",
      "104.22.54.228"
    ],
    [
      "docs.tryhackme.com",
      "Unknown"
    ],
    [
      "monitoring.tryhackme.com",
      "Unknown"
    ],
    [
      "assets.tryhackme.com",
      "Unknown"
    ],
    [
      "insights-proxy-worker.tryhackme.com",
      "Unknown"
    ],
    [
      "careers.tryhackme.com",
      "Unknown"
    ],
    [
      "store.tryhackme.com",
      "Unknown"
    ],
    [
      "remote-eu-1.tryhackme.com",
      "Unknown"
    ],
    [
      "blog.tryhackme.com",
      "Unknown"
    ],
    [
      "help.tryhackme.com",
      "Unknown"
    ]
  ],
  "live_subdomains": [
    {
      "subdomain": "store.tryhackme.com",
      "ip": "Unknown",
      "status_code": 200,
      "protocol": "https",
      "title": "TryHackMe Store",
      "server": "cloudflare",
      "technology": [],
      "response_time": 0.513976,
      "content_length": 150977
    },
    {
      "subdomain": "assets.tryhackme.com",
      "ip": "Unknown",
      "status_code": 403,
      "protocol": "https",
      "title": "No Title",
      "server": "AmazonS3",
      "technology": [
        "Missing security headers: x-frame-options, x-xss-protection, x-content-type-options"
      ],
      "response_time": 0.918398,
      "content_length": 111
    },
    {
      "subdomain": "auth.tryhackme.com",
      "ip": "Unknown",
      "status_code": 200,
      "protocol": "https",
      "title": "No Title",
      "server": "cloudflare",
      "technology": [],
      "response_time": 0.96499,
      "content_length": 2
    },
    {
      "subdomain": "setup.auth.tryhackme.com",
      "ip": "Unknown",
      "status_code": 200,
      "protocol": "https",
      "title": "No Title",
      "server": "cloudflare",
      "technology": [
        "Missing security headers: x-xss-protection, x-content-type-options"
      ],
      "response_time": 1.061369,
      "content_length": 1882
    },
    {
      "subdomain": "careers.tryhackme.com",
      "ip": "Unknown",
      "status_code": 200,
      "protocol": "https",
      "title": "Welcome to TryHackMe Careers - TryHackMe",
      "server": "Unknown",
      "technology": [],
      "response_time": 0.922008,
      "content_length": 67380
    },
    {
      "subdomain": "resources.tryhackme.com",
      "ip": "Unknown",
      "status_code": 200,
      "protocol": "https",
      "title": "aws-cloud-security-training",
      "server": "Unknown",
      "technology": [
        "Missing security headers: x-frame-options, x-xss-protection, x-content-type-options"
      ],
      "response_time": 1.413359,
      "content_length": 2634
    },
    {
      "subdomain": "business.tryhackme.com",
      "ip": "Unknown",
      "status_code": 200,
      "protocol": "https",
      "title": "Advanced Cyber Security Training for Teams | Trusted by 4M+ Users",
      "server": "cloudflare",
      "technology": [
        "Missing security headers: x-frame-options, x-xss-protection"
      ],
      "response_time": 1.9819,
      "content_length": 204810
    },
    {
      "subdomain": "cancel.tryhackme.com",
      "ip": "Unknown",
      "status_code": 200,
      "protocol": "https",
      "title": "Retention",
      "server": "Caddy, Brightback",
      "technology": [
        "React",
        "Missing security headers: x-frame-options, x-xss-protection, x-content-type-options"
      ],
      "response_time": 0.857746,
      "content_length": 15681
    },
    {
      "subdomain": "lp.tryhackme.com",
      "ip": "Unknown",
      "status_code": 404,
      "protocol": "https",
      "title": "No Title",
      "server": "cloudflare",
      "technology": [
        "Missing security headers: x-frame-options, x-xss-protection"
      ],
      "response_time": 2.8057,
      "content_length": 44875
    }
  ],
  "summary": {
    "technologies": {
      "Missing security headers: x-frame-options, x-xss-protection, x-content-type-options": 3,
      "Missing security headers: x-xss-protection, x-content-type-options": 1,
      "Missing security headers: x-frame-options, x-xss-protection": 2,
      "React": 1
    },
    "security_issues": [
      {
        "subdomain": "assets.tryhackme.com",
        "issues": [
          "Missing security headers"
        ]
      },
      {
        "subdomain": "setup.auth.tryhackme.com",
        "issues": [
          "Missing security headers"
        ]
      },
      {
        "subdomain": "resources.tryhackme.com",
        "issues": [
          "Missing security headers"
        ]
      },
      {
        "subdomain": "business.tryhackme.com",
        "issues": [
          "Missing security headers"
        ]
      },
      {
        "subdomain": "cancel.tryhackme.com",
        "issues": [
          "Missing security headers"
        ]
      },
      {
        "subdomain": "lp.tryhackme.com",
        "issues": [
          "Missing security headers"
        ]
      }
    ],
    "recommendations": [
      "Implement proper security headers (X-Frame-Options, X-XSS-Protection, etc.)",
      "Ensure all subdomains use HTTPS with valid certificates",
      "Remove or restrict access to development/staging environments",
      "Implement proper access controls for admin interfaces",
      "Regular security scanning and penetration testing",
      "Monitor certificate transparency logs for unauthorized certificates"
    ]
  }
}